gregory/__init__.py
gregory/_version.py
gregory/main.py
gregory/dataclass/__init__.py
gregory/dataclass/time_series_data.py
gregory/granularity/__init__.py
gregory/granularity/granularity.py
gregory/granularity/granularity_factory.py
gregory/granularity/utils.py
gregory/timeseries/__init__.py
gregory/timeseries/batches.py
gregory/timeseries/expr.py
gregory/timeseries/processing.py
gregory/timeseries/time_series.py
gregory/util/__init__.py
gregory/util/agenda.py
gregory/util/bisect.py
gregory/util/decorators.py
gregory/util/dictionaries.py
gregory/util/relativedelta.py
test/__init__.py
test/test_time_series.py
test/test_time_series_batch.py
test/test_time_series_expr.py
test/test_time_series_processing.py
test/test_util_dictionaries.py
test/utils.py
gregory-3.1.1.dist-info/LICENSE
gregory-3.1.1.dist-info/METADATA
gregory-3.1.1.dist-info/WHEEL
gregory-3.1.1.dist-info/top_level.txt
gregory-3.1.1.dist-info/RECORD
