Metadata-Version: 2.1
Name: gregory
Version: 3.1.1
Summary: Python framework to manage time series structured as one-level dictionaries
Home-page: https://github.com/SynStratos/gregory
Author: Luca Spartera
Author-email: synstratos.dev@gmail.com
Keywords: time series,ts,timeseries,temporal data
Classifier: Programming Language :: Python :: 3
Classifier: Programming Language :: Python :: 3.8
Classifier: Programming Language :: Python :: 3.9
Classifier: Programming Language :: Python :: 3.10
Classifier: License :: OSI Approved :: MIT License
Classifier: Operating System :: OS Independent
Classifier: Natural Language :: English
Requires-Python: >=3.8, <3.11
License-File: LICENSE
Requires-Dist: outatime (<4.0.0,>=3.2.1)
Requires-Dist: python-dateutil
Requires-Dist: statsmodels
Requires-Dist: numpy
Requires-Dist: scipy
